
{
  "illustration": [
    {
      "filename": "WesternComic.png",
      "title": "Railway Outlaw Crew",
      "description": "Comic series concept illustration"
    },
    {
      "filename": "WarfConcept.png",
      "title": "Mystery on the Warf",
      "description": "Comic series concept illustration"
    },
    {
      "filename": "Robuttnik.png",
      "title": "Robotnik",
      "description": "Fan Work"
    },
    {
      "filename": "Kudzu.png",
      "title": "Kudzu",
      "description": "Album Artwork"
    },
    {
      "filename": "Link_Faceoff.png",
      "title": "Link Faces the Darknut",
      "description": "Fan Work"
    },
    {
      "filename": "SamusPirates.png",
      "title": "Samus Aran - Surrounded",
      "description": "Fan Work"
    },
    {
      "filename": "illustration-bait.png",
      "title": "Bait",
      "description": ""
    },
    {
      "filename": "JammerDoor.png",
      "title": "Let us In Already",
      "description": "Fan Work"
    },
    {
      "filename": "Amychase.png",
      "title": "Amy Chased",
      "description": "Fan Work"
    },
    {
      "filename": "Tails-Teacup.png",
      "title": "Tails Teacup",
      "description": "Fan Work"
    },
    {
      "filename": "illustration-Empty.png",
      "title": "Empty",
      "description": ""
    }
  ]
}
